{
  "protocol_version" : "0.0.6",
  "configuration" : {
    "version" : "(6.13.0) (explicit/7ea6b90eb94)",
    "tlc" : "__thread",
    "sigsgev" : "normal",
    "notifications" : "kqueue",
    "architecture" : "arm64",
    "disabled_features" : "com,shared_perfcounters",
    "smallconfig" : "disabled",
    "bigarrays" : "disabled",
    "softdebug" : "enabled",
    "interpreter" : "enabled",
    "llvm_support" : "disabled",
    "suspend" : "preemptive"
  },
  "memory" : {
    "Resident Size" : "480788480",
    "Virtual Size" : "422945800192",
    "minor_gc_time" : "0",
    "major_gc_time" : "18968912",
    "minor_gc_count" : "0",
    "major_gc_count" : "172",
    "major_gc_time_concurrent" : "0"
 },
  "threads" : [
 {
    "is_managed" : false,
    "offset_free_hash" : "0x0",
    "offset_rich_hash" : "0x0",
    "crashed" : false,
    "native_thread_id" : "0x2c61df000",
    "thread_info_addr" : "0x328b06600",
    "thread_name" : "Thread Pool Worker",
    "ctx" : {
      "IP" : "0x1a37c4924",
      "SP" : "0x2c61dedb0",
      "BP" : "0x2c61dee50"
  },
    "unmanaged_frames" : [
  {
      "is_managed" : "false",
      "native_address" : "0x13d705ec0",
      "native_offset" : "0x00000"
   }
,
  {
      "is_managed" : "false",
      "native_address" : "0x13d83c8cc",
      "native_offset" : "0x00000"
   }
,
  {
      "is_managed" : "false",
      "native_address" : "0x13d83cc28",
      "native_offset" : "0x00000"
   }
,
  {
      "is_managed" : "false",
      "native_address" : "0x13d83c9f0",
      "native_offset" : "0x00000"
   }
,
  {
      "is_managed" : "false",
      "native_address" : "0x13d746dc8",
      "native_offset" : "0x00000"
   }
,
  {
      "is_managed" : "false",
      "native_address" : "0x1a38194c4",
      "native_offset" : "0x00000"
   }
,
  {
      "is_managed" : "false",
      "native_address" : "0x13d794e4c",
      "native_offset" : "0x00000"
   }
,
  {
      "is_managed" : "false",
      "native_address" : "0x13d83d638",
      "native_offset" : "0x00000"
   }
,
  {
      "is_managed" : "false",
      "native_address" : "0x13d83d4e4",
      "native_offset" : "0x00000"
   }
,
  {
      "is_managed" : "false",
      "native_address" : "0x13d8bcd30",
      "native_offset" : "0x00000"
   }
,
  {
      "is_managed" : "false",
      "native_address" : "0x13d8bccb8",
      "native_offset" : "0x00000"
   }
,
  {
      "is_managed" : "false",
      "native_address" : "0x1a380226c",
      "native_offset" : "0x00000"
   }
,
  {
      "is_managed" : "false",
      "native_address" : "0x1a37fd08c",
      "native_offset" : "0x00000"
   }

  ]
 },
 {
    "is_managed" : false,
    "offset_free_hash" : "0x0",
    "offset_rich_hash" : "0x0",
    "crashed" : false,
    "native_thread_id" : "0x17f9c7000",
    "thread_info_addr" : "0x14c1fd200",
    "thread_name" : "Finalizer",
    "ctx" : {
      "IP" : "0x1a37c490c",
      "SP" : "0x17f9c6dd0",
      "BP" : "0x17f9c6e50"
  },
    "unmanaged_frames" : [
  {
      "is_managed" : "false",
      "native_address" : "0x13d705ec0",
      "native_offset" : "0x00000"
   }
,
  {
      "is_managed" : "false",
      "native_address" : "0x13d83c8cc",
      "native_offset" : "0x00000"
   }
,
  {
      "is_managed" : "false",
      "native_address" : "0x13d83cc28",
      "native_offset" : "0x00000"
   }
,
  {
      "is_managed" : "false",
      "native_address" : "0x13d83c9f0",
      "native_offset" : "0x00000"
   }
,
  {
      "is_managed" : "false",
      "native_address" : "0x13d746dc8",
      "native_offset" : "0x00000"
   }
,
  {
      "is_managed" : "false",
      "native_address" : "0x1a38194c4",
      "native_offset" : "0x00000"
   }
,
  {
      "is_managed" : "false",
      "native_address" : "0x13d8763b4",
      "native_offset" : "0x00000"
   }
,
  {
      "is_managed" : "false",
      "native_address" : "0x13d83d638",
      "native_offset" : "0x00000"
   }
,
  {
      "is_managed" : "false",
      "native_address" : "0x13d83d4e4",
      "native_offset" : "0x00000"
   }
,
  {
      "is_managed" : "false",
      "native_address" : "0x13d8bcd30",
      "native_offset" : "0x00000"
   }
,
  {
      "is_managed" : "false",
      "native_address" : "0x13d8bccb8",
      "native_offset" : "0x00000"
   }
,
  {
      "is_managed" : "false",
      "native_address" : "0x1a380226c",
      "native_offset" : "0x00000"
   }
,
  {
      "is_managed" : "false",
      "native_address" : "0x1a37fd08c",
      "native_offset" : "0x00000"
   }

  ]
 },
 {
    "is_managed" : false,
    "offset_free_hash" : "0x0",
    "offset_rich_hash" : "0x0",
    "crashed" : false,
    "native_thread_id" : "0x2c7dc7000",
    "thread_info_addr" : "0x2b07cbe00",
    "thread_name" : "Thread Pool I/O Selector",
    "ctx" : {
      "IP" : "0x1a37cf5b8",
      "SP" : "0x2c7dc6ae0",
      "BP" : "0x2c7dc6ce0"
  },
    "unmanaged_frames" : [
  {
      "is_managed" : "false",
      "native_address" : "0x13d705ec0",
      "native_offset" : "0x00000"
   }
,
  {
      "is_managed" : "false",
      "native_address" : "0x13d83c8cc",
      "native_offset" : "0x00000"
   }
,
  {
      "is_managed" : "false",
      "native_address" : "0x13d83cc28",
      "native_offset" : "0x00000"
   }
,
  {
      "is_managed" : "false",
      "native_address" : "0x13d83c9f0",
      "native_offset" : "0x00000"
   }
,
  {
      "is_managed" : "false",
      "native_address" : "0x13d746dc8",
      "native_offset" : "0x00000"
   }
,
  {
      "is_managed" : "false",
      "native_address" : "0x1a38194c4",
      "native_offset" : "0x00000"
   }
,
  {
      "is_managed" : "false",
      "native_address" : "0x13d88e950",
      "native_offset" : "0x00000"
   }
,
  {
      "is_managed" : "false",
      "native_address" : "0x13d841e00",
      "native_offset" : "0x00000"
   }
,
  {
      "is_managed" : "false",
      "native_address" : "0x13d841818",
      "native_offset" : "0x00000"
   }
,
  {
      "is_managed" : "false",
      "native_address" : "0x13d83d638",
      "native_offset" : "0x00000"
   }
,
  {
      "is_managed" : "false",
      "native_address" : "0x13d83d4e4",
      "native_offset" : "0x00000"
   }
,
  {
      "is_managed" : "false",
      "native_address" : "0x13d8bcd30",
      "native_offset" : "0x00000"
   }
,
  {
      "is_managed" : "false",
      "native_address" : "0x13d8bccb8",
      "native_offset" : "0x00000"
   }
,
  {
      "is_managed" : "false",
      "native_address" : "0x1a380226c",
      "native_offset" : "0x00000"
   }
,
  {
      "is_managed" : "false",
      "native_address" : "0x1a37fd08c",
      "native_offset" : "0x00000"
   }

  ]
 },
 {
    "is_managed" : true,
    "offset_free_hash" : "0x1224727402",
    "offset_rich_hash" : "0x12247275cb",
    "crashed" : false,
    "native_thread_id" : "0x2cc6f3000",
    "thread_info_addr" : "0x14a887e00",
    "thread_name" : "Timer-Scheduler",
    "ctx" : {
      "IP" : "0x1a37c8290",
      "SP" : "0x2cc6f1ed0",
      "BP" : "0x2cc6f1f60"
  },
    "managed_frames" : [
  {
      "is_managed" : "false",
      "native_address" : "unregistered"
   }
,
  {
      "is_managed" : "true",
      "guid" : "E38A6D3E-E47C-43EB-9B2E-49C63FC0AA48",
      "token" : "0x00000",
      "native_offset" : "0x0",
      "filename" : "mscorlib.dll",
      "sizeofimage" : "0x470000",
      "timestamp" : "0xaf0ada7a",
      "il_offset" : "0xffffffff"
   }
,
  {
      "is_managed" : "true",
      "guid" : "E38A6D3E-E47C-43EB-9B2E-49C63FC0AA48",
      "token" : "0x60020b2",
      "native_offset" : "0x0",
      "filename" : "mscorlib.dll",
      "sizeofimage" : "0x470000",
      "timestamp" : "0xaf0ada7a",
      "il_offset" : "0x00044"
   }
,
  {
      "is_managed" : "true",
      "guid" : "E38A6D3E-E47C-43EB-9B2E-49C63FC0AA48",
      "token" : "0x600209e",
      "native_offset" : "0x0",
      "filename" : "mscorlib.dll",
      "sizeofimage" : "0x470000",
      "timestamp" : "0xaf0ada7a",
      "il_offset" : "0x00014"
   }
,
  {
      "is_managed" : "true",
      "guid" : "E38A6D3E-E47C-43EB-9B2E-49C63FC0AA48",
      "token" : "0x600209d",
      "native_offset" : "0x0",
      "filename" : "mscorlib.dll",
      "sizeofimage" : "0x470000",
      "timestamp" : "0xaf0ada7a",
      "il_offset" : "0x00000"
   }
,
  {
      "is_managed" : "true",
      "guid" : "E38A6D3E-E47C-43EB-9B2E-49C63FC0AA48",
      "token" : "0x6002098",
      "native_offset" : "0x0",
      "filename" : "mscorlib.dll",
      "sizeofimage" : "0x470000",
      "timestamp" : "0xaf0ada7a",
      "il_offset" : "0x00019"
   }
,
  {
      "is_managed" : "true",
      "guid" : "E38A6D3E-E47C-43EB-9B2E-49C63FC0AA48",
      "token" : "0x600209b",
      "native_offset" : "0x0",
      "filename" : "mscorlib.dll",
      "sizeofimage" : "0x470000",
      "timestamp" : "0xaf0ada7a",
      "il_offset" : "0x00000"
   }
,
  {
      "is_managed" : "true",
      "guid" : "E38A6D3E-E47C-43EB-9B2E-49C63FC0AA48",
      "token" : "0x600215a",
      "native_offset" : "0x0",
      "filename" : "mscorlib.dll",
      "sizeofimage" : "0x470000",
      "timestamp" : "0xaf0ada7a",
      "il_offset" : "0x0003c"
   }
,
  {
      "is_managed" : "true",
      "guid" : "E38A6D3E-E47C-43EB-9B2E-49C63FC0AA48",
      "token" : "0x6001f7d",
      "native_offset" : "0x0",
      "filename" : "mscorlib.dll",
      "sizeofimage" : "0x470000",
      "timestamp" : "0xaf0ada7a",
      "il_offset" : "0x00014"
   }
,
  {
      "is_managed" : "true",
      "guid" : "E38A6D3E-E47C-43EB-9B2E-49C63FC0AA48",
      "token" : "0x6001f25",
      "native_offset" : "0x0",
      "filename" : "mscorlib.dll",
      "sizeofimage" : "0x470000",
      "timestamp" : "0xaf0ada7a",
      "il_offset" : "0x00071"
   }
,
  {
      "is_managed" : "true",
      "guid" : "E38A6D3E-E47C-43EB-9B2E-49C63FC0AA48",
      "token" : "0x6001f23",
      "native_offset" : "0x0",
      "filename" : "mscorlib.dll",
      "sizeofimage" : "0x470000",
      "timestamp" : "0xaf0ada7a",
      "il_offset" : "0x00000"
   }
,
  {
      "is_managed" : "true",
      "guid" : "E38A6D3E-E47C-43EB-9B2E-49C63FC0AA48",
      "token" : "0x6001f22",
      "native_offset" : "0x0",
      "filename" : "mscorlib.dll",
      "sizeofimage" : "0x470000",
      "timestamp" : "0xaf0ada7a",
      "il_offset" : "0x0002b"
   }
,
  {
      "is_managed" : "true",
      "guid" : "E38A6D3E-E47C-43EB-9B2E-49C63FC0AA48",
      "token" : "0x6001f7f",
      "native_offset" : "0x0",
      "filename" : "mscorlib.dll",
      "sizeofimage" : "0x470000",
      "timestamp" : "0xaf0ada7a",
      "il_offset" : "0x00008"
   }
,
  {
      "is_managed" : "true",
      "guid" : "E38A6D3E-E47C-43EB-9B2E-49C63FC0AA48",
      "token" : "0x00000",
      "native_offset" : "0x0",
      "filename" : "mscorlib.dll",
      "sizeofimage" : "0x470000",
      "timestamp" : "0xaf0ada7a",
      "il_offset" : "0x00065"
   }

  ],
  "unmanaged_frames" : [
 {
    "is_managed" : "false",
    "native_address" : "0x13d705ec0",
    "native_offset" : "0x00000"
  }
,
 {
    "is_managed" : "false",
    "native_address" : "0x13d83c8cc",
    "native_offset" : "0x00000"
  }
,
 {
    "is_managed" : "false",
    "native_address" : "0x13d83cc28",
    "native_offset" : "0x00000"
  }
,
 {
    "is_managed" : "false",
    "native_address" : "0x13d83c9f0",
    "native_offset" : "0x00000"
  }
,
 {
    "is_managed" : "false",
    "native_address" : "0x13d746dc8",
    "native_offset" : "0x00000"
  }
,
 {
    "is_managed" : "false",
    "native_address" : "0x1a38194c4",
    "native_offset" : "0x00000"
  }
,
 {
    "is_managed" : "false",
    "native_address" : "0x1a3802868",
    "native_offset" : "0x00000"
  }
,
 {
    "is_managed" : "false",
    "native_address" : "0x13d88beac",
    "native_offset" : "0x00000"
  }
,
 {
    "is_managed" : "false",
    "native_address" : "0x13d8485f4",
    "native_offset" : "0x00000"
  }
,
 {
    "is_managed" : "false",
    "native_address" : "0x13d848428",
    "native_offset" : "0x00000"
  }
,
 {
    "is_managed" : "false",
    "native_address" : "0x13d8486c0",
    "native_offset" : "0x00000"
  }
,
 {
    "is_managed" : "false",
    "native_address" : "0x13d837c6c",
    "native_offset" : "0x00000"
  }
,
 {
    "is_managed" : "false",
    "native_address" : "0x13d7e24f8",
    "native_offset" : "0x00000"
  }
,
 {
    "is_managed" : "true",
    "guid" : "E38A6D3E-E47C-43EB-9B2E-49C63FC0AA48",
    "token" : "0x00000",
    "native_offset" : "0x0",
    "filename" : "mscorlib.dll",
    "sizeofimage" : "0x470000",
    "timestamp" : "0xaf0ada7a",
    "il_offset" : "0x00000"
  }
,
 {
    "is_managed" : "true",
    "guid" : "E38A6D3E-E47C-43EB-9B2E-49C63FC0AA48",
    "token" : "0x60020b2",
    "native_offset" : "0x0",
    "filename" : "mscorlib.dll",
    "sizeofimage" : "0x470000",
    "timestamp" : "0xaf0ada7a",
    "il_offset" : "0x00000"
  }
,
 {
    "is_managed" : "true",
    "guid" : "E38A6D3E-E47C-43EB-9B2E-49C63FC0AA48",
    "token" : "0x600209e",
    "native_offset" : "0x0",
    "filename" : "mscorlib.dll",
    "sizeofimage" : "0x470000",
    "timestamp" : "0xaf0ada7a",
    "il_offset" : "0x00000"
  }
,
 {
    "is_managed" : "true",
    "guid" : "E38A6D3E-E47C-43EB-9B2E-49C63FC0AA48",
    "token" : "0x600209d",
    "native_offset" : "0x0",
    "filename" : "mscorlib.dll",
    "sizeofimage" : "0x470000",
    "timestamp" : "0xaf0ada7a",
    "il_offset" : "0x00000"
  }
,
 {
    "is_managed" : "true",
    "guid" : "E38A6D3E-E47C-43EB-9B2E-49C63FC0AA48",
    "token" : "0x6002098",
    "native_offset" : "0x0",
    "filename" : "mscorlib.dll",
    "sizeofimage" : "0x470000",
    "timestamp" : "0xaf0ada7a",
    "il_offset" : "0x00000"
  }
,
 {
    "is_managed" : "true",
    "guid" : "E38A6D3E-E47C-43EB-9B2E-49C63FC0AA48",
    "token" : "0x600209b",
    "native_offset" : "0x0",
    "filename" : "mscorlib.dll",
    "sizeofimage" : "0x470000",
    "timestamp" : "0xaf0ada7a",
    "il_offset" : "0x00000"
  }
,
 {
    "is_managed" : "true",
    "guid" : "E38A6D3E-E47C-43EB-9B2E-49C63FC0AA48",
    "token" : "0x600215a",
    "native_offset" : "0x0",
    "filename" : "mscorlib.dll",
    "sizeofimage" : "0x470000",
    "timestamp" : "0xaf0ada7a",
    "il_offset" : "0x00000"
  }
,
 {
    "is_managed" : "true",
    "guid" : "E38A6D3E-E47C-43EB-9B2E-49C63FC0AA48",
    "token" : "0x6001f7d",
    "native_offset" : "0x0",
    "filename" : "mscorlib.dll",
    "sizeofimage" : "0x470000",
    "timestamp" : "0xaf0ada7a",
    "il_offset" : "0x00000"
  }
,
 {
    "is_managed" : "true",
    "guid" : "E38A6D3E-E47C-43EB-9B2E-49C63FC0AA48",
    "token" : "0x6001f25",
    "native_offset" : "0x0",
    "filename" : "mscorlib.dll",
    "sizeofimage" : "0x470000",
    "timestamp" : "0xaf0ada7a",
    "il_offset" : "0x00000"
  }
,
 {
    "is_managed" : "true",
    "guid" : "E38A6D3E-E47C-43EB-9B2E-49C63FC0AA48",
    "token" : "0x6001f23",
    "native_offset" : "0x0",
    "filename" : "mscorlib.dll",
    "sizeofimage" : "0x470000",
    "timestamp" : "0xaf0ada7a",
    "il_offset" : "0x00000"
  }
,
 {
    "is_managed" : "true",
    "guid" : "E38A6D3E-E47C-43EB-9B2E-49C63FC0AA48",
    "token" : "0x6001f22",
    "native_offset" : "0x0",
    "filename" : "mscorlib.dll",
    "sizeofimage" : "0x470000",
    "timestamp" : "0xaf0ada7a",
    "il_offset" : "0x00000"
  }
,
 {
    "is_managed" : "true",
    "guid" : "E38A6D3E-E47C-43EB-9B2E-49C63FC0AA48",
    "token" : "0x6001f7f",
    "native_offset" : "0x0",
    "filename" : "mscorlib.dll",
    "sizeofimage" : "0x470000",
    "timestamp" : "0xaf0ada7a",
    "il_offset" : "0x00000"
  }
,
 {
    "is_managed" : "true",
    "guid" : "E38A6D3E-E47C-43EB-9B2E-49C63FC0AA48",
    "token" : "0x00000",
    "native_offset" : "0x0",
    "filename" : "mscorlib.dll",
    "sizeofimage" : "0x470000",
    "timestamp" : "0xaf0ada7a",
    "il_offset" : "0x00000"
  }
,
 {
    "is_managed" : "false",
    "native_address" : "0x13d695b74",
    "native_offset" : "0x00000"
  }
,
 {
    "is_managed" : "false",
    "native_address" : "0x13d81b7ec",
    "native_offset" : "0x00000"
  }
,
 {
    "is_managed" : "false",
    "native_address" : "0x13d81d3e8",
    "native_offset" : "0x00000"
  }
,
 {
    "is_managed" : "false",
    "native_address" : "0x13d83d72c",
    "native_offset" : "0x00000"
  }
,
 {
    "is_managed" : "false",
    "native_address" : "0x13d83d4e4",
    "native_offset" : "0x00000"
  }
,
 {
    "is_managed" : "false",
    "native_address" : "0x13d8bcd30",
    "native_offset" : "0x00000"
  }
,
 {
    "is_managed" : "false",
    "native_address" : "0x13d8bccb8",
    "native_offset" : "0x00000"
  }
,
 {
    "is_managed" : "false",
    "native_address" : "0x1a380226c",
    "native_offset" : "0x00000"
  }
,
 {
    "is_managed" : "false",
    "native_address" : "0x1a37fd08c",
    "native_offset" : "0x00000"
  }

 ]
},
{
  "is_managed" : true,
  "offset_free_hash" : "0xfb24c8f6a",
  "offset_rich_hash" : "0xfb24c90f3",
  "crashed" : false,
  "native_thread_id" : "0x2e4e2b000",
  "thread_info_addr" : "0x32818e200",
  "thread_name" : "tid_1f507",
  "ctx" : {
    "IP" : "0x1a37c8290",
    "SP" : "0x2e4e2a530",
    "BP" : "0x2e4e2a5c0"
 },
  "managed_frames" : [
 {
    "is_managed" : "false",
    "native_address" : "unregistered"
  }
,
 {
    "is_managed" : "true",
    "guid" : "E38A6D3E-E47C-43EB-9B2E-49C63FC0AA48",
    "token" : "0x00000",
    "native_offset" : "0x0",
    "filename" : "mscorlib.dll",
    "sizeofimage" : "0x470000",
    "timestamp" : "0xaf0ada7a",
    "il_offset" : "0xffffffff"
  }
,
 {
    "is_managed" : "true",
    "guid" : "E38A6D3E-E47C-43EB-9B2E-49C63FC0AA48",
    "token" : "0x6001f5d",
    "native_offset" : "0x0",
    "filename" : "mscorlib.dll",
    "sizeofimage" : "0x470000",
    "timestamp" : "0xaf0ada7a",
    "il_offset" : "0x0002f"
  }
,
 {
    "is_managed" : "true",
    "guid" : "E38A6D3E-E47C-43EB-9B2E-49C63FC0AA48",
    "token" : "0x6001f50",
    "native_offset" : "0x0",
    "filename" : "mscorlib.dll",
    "sizeofimage" : "0x470000",
    "timestamp" : "0xaf0ada7a",
    "il_offset" : "0x0000e"
  }
,
 {
    "is_managed" : "true",
    "guid" : "E38A6D3E-E47C-43EB-9B2E-49C63FC0AA48",
    "token" : "0x6001f52",
    "native_offset" : "0x0",
    "filename" : "mscorlib.dll",
    "sizeofimage" : "0x470000",
    "timestamp" : "0xaf0ada7a",
    "il_offset" : "0x00000"
  }
,
 {
    "is_managed" : "true",
    "guid" : "C367E0BC-B6D4-43AA-B744-A88F98B1F317",
    "token" : "0x60057d3",
    "native_offset" : "0x0",
    "filename" : "unityplastic.dll",
    "sizeofimage" : "0x4c8000",
    "timestamp" : "0x62434843",
    "il_offset" : "0x00030"
  }
,
 {
    "is_managed" : "true",
    "guid" : "E38A6D3E-E47C-43EB-9B2E-49C63FC0AA48",
    "token" : "0x6001f7d",
    "native_offset" : "0x0",
    "filename" : "mscorlib.dll",
    "sizeofimage" : "0x470000",
    "timestamp" : "0xaf0ada7a",
    "il_offset" : "0x00014"
  }
,
 {
    "is_managed" : "true",
    "guid" : "E38A6D3E-E47C-43EB-9B2E-49C63FC0AA48",
    "token" : "0x6001f25",
    "native_offset" : "0x0",
    "filename" : "mscorlib.dll",
    "sizeofimage" : "0x470000",
    "timestamp" : "0xaf0ada7a",
    "il_offset" : "0x00071"
  }
,
 {
    "is_managed" : "true",
    "guid" : "E38A6D3E-E47C-43EB-9B2E-49C63FC0AA48",
    "token" : "0x6001f23",
    "native_offset" : "0x0",
    "filename" : "mscorlib.dll",
    "sizeofimage" : "0x470000",
    "timestamp" : "0xaf0ada7a",
    "il_offset" : "0x00000"
  }
,
 {
    "is_managed" : "true",
    "guid" : "E38A6D3E-E47C-43EB-9B2E-49C63FC0AA48",
    "token" : "0x6001f22",
    "native_offset" : "0x0",
    "filename" : "mscorlib.dll",
    "sizeofimage" : "0x470000",
    "timestamp" : "0xaf0ada7a",
    "il_offset" : "0x0002b"
  }
,
 {
    "is_managed" : "true",
    "guid" : "E38A6D3E-E47C-43EB-9B2E-49C63FC0AA48",
    "token" : "0x6001f7f",
    "native_offset" : "0x0",
    "filename" : "mscorlib.dll",
    "sizeofimage" : "0x470000",
    "timestamp" : "0xaf0ada7a",
    "il_offset" : "0x00008"
  }
,
 {
    "is_managed" : "true",
    "guid" : "E38A6D3E-E47C-43EB-9B2E-49C63FC0AA48",
    "token" : "0x00000",
    "native_offset" : "0x0",
    "filename" : "mscorlib.dll",
    "sizeofimage" : "0x470000",
    "timestamp" : "0xaf0ada7a",
    "il_offset" : "0x00065"
  }

 ],
"unmanaged_frames" : [
{
  "is_managed" : "false",
  "native_address" : "0x13d705ec0",
  "native_offset" : "0x00000"
 }
,
{
  "is_managed" : "false",
  "native_address" : "0x13d83c8cc",
  "native_offset" : "0x00000"
 }
,
{
  "is_managed" : "false",
  "native_address" : "0x13d83cc28",
  "native_offset" : "0x00000"
 }
,
{
  "is_managed" : "false",
  "native_address" : "0x13d83c9f0",
  "native_offset" : "0x00000"
 }
,
{
  "is_managed" : "false",
  "native_address" : "0x13d746dc8",
  "native_offset" : "0x00000"
 }
,
{
  "is_managed" : "false",
  "native_address" : "0x1a38194c4",
  "native_offset" : "0x00000"
 }
,
{
  "is_managed" : "false",
  "native_address" : "0x1a3802868",
  "native_offset" : "0x00000"
 }
,
{
  "is_managed" : "false",
  "native_address" : "0x13d88beac",
  "native_offset" : "0x00000"
 }
,
{
  "is_managed" : "false",
  "native_address" : "0x13d8485f4",
  "native_offset" : "0x00000"
 }
,
{
  "is_managed" : "false",
  "native_address" : "0x13d848428",
  "native_offset" : "0x00000"
 }
,
{
  "is_managed" : "false",
  "native_address" : "0x13d8776f8",
  "native_offset" : "0x00000"
 }
,
{
  "is_managed" : "false",
  "native_address" : "0x13d7e0dfc",
  "native_offset" : "0x00000"
 }
,
{
  "is_managed" : "true",
  "guid" : "E38A6D3E-E47C-43EB-9B2E-49C63FC0AA48",
  "token" : "0x00000",
  "native_offset" : "0x0",
  "filename" : "mscorlib.dll",
  "sizeofimage" : "0x470000",
  "timestamp" : "0xaf0ada7a",
  "il_offset" : "0x00000"
 }
,
{
  "is_managed" : "true",
  "guid" : "E38A6D3E-E47C-43EB-9B2E-49C63FC0AA48",
  "token" : "0x6001f5d",
  "native_offset" : "0x0",
  "filename" : "mscorlib.dll",
  "sizeofimage" : "0x470000",
  "timestamp" : "0xaf0ada7a",
  "il_offset" : "0x00000"
 }
,
{
  "is_managed" : "true",
  "guid" : "E38A6D3E-E47C-43EB-9B2E-49C63FC0AA48",
  "token" : "0x6001f50",
  "native_offset" : "0x0",
  "filename" : "mscorlib.dll",
  "sizeofimage" : "0x470000",
  "timestamp" : "0xaf0ada7a",
  "il_offset" : "0x00000"
 }
,
{
  "is_managed" : "true",
  "guid" : "E38A6D3E-E47C-43EB-9B2E-49C63FC0AA48",
  "token" : "0x6001f52",
  "native_offset" : "0x0",
  "filename" : "mscorlib.dll",
  "sizeofimage" : "0x470000",
  "timestamp" : "0xaf0ada7a",
  "il_offset" : "0x00000"
 }
,
{
  "is_managed" : "true",
  "guid" : "C367E0BC-B6D4-43AA-B744-A88F98B1F317",
  "token" : "0x60057d3",
  "native_offset" : "0x0",
  "filename" : "unityplastic.dll",
  "sizeofimage" : "0x4c8000",
  "timestamp" : "0x62434843",
  "il_offset" : "0x00000"
 }
,
{
  "is_managed" : "true",
  "guid" : "E38A6D3E-E47C-43EB-9B2E-49C63FC0AA48",
  "token" : "0x6001f7d",
  "native_offset" : "0x0",
  "filename" : "mscorlib.dll",
  "sizeofimage" : "0x470000",
  "timestamp" : "0xaf0ada7a",
  "il_offset" : "0x00000"
 }
,
{
  "is_managed" : "true",
  "guid" : "E38A6D3E-E47C-43EB-9B2E-49C63FC0AA48",
  "token" : "0x6001f25",
  "native_offset" : "0x0",
  "filename" : "mscorlib.dll",
  "sizeofimage" : "0x470000",
  "timestamp" : "0xaf0ada7a",
  "il_offset" : "0x00000"
 }
,
{
  "is_managed" : "true",
  "guid" : "E38A6D3E-E47C-43EB-9B2E-49C63FC0AA48",
  "token" : "0x6001f23",
  "native_offset" : "0x0",
  "filename" : "mscorlib.dll",
  "sizeofimage" : "0x470000",
  "timestamp" : "0xaf0ada7a",
  "il_offset" : "0x00000"
 }
,
{
  "is_managed" : "true",
  "guid" : "E38A6D3E-E47C-43EB-9B2E-49C63FC0AA48",
  "token" : "0x6001f22",
  "native_offset" : "0x0",
  "filename" : "mscorlib.dll",
  "sizeofimage" : "0x470000",
  "timestamp" : "0xaf0ada7a",
  "il_offset" : "0x00000"
 }
,
{
  "is_managed" : "true",
  "guid" : "E38A6D3E-E47C-43EB-9B2E-49C63FC0AA48",
  "token" : "0x6001f7f",
  "native_offset" : "0x0",
  "filename" : "mscorlib.dll",
  "sizeofimage" : "0x470000",
  "timestamp" : "0xaf0ada7a",
  "il_offset" : "0x00000"
 }
,
{
  "is_managed" : "true",
  "guid" : "E38A6D3E-E47C-43EB-9B2E-49C63FC0AA48",
  "token" : "0x00000",
  "native_offset" : "0x0",
  "filename" : "mscorlib.dll",
  "sizeofimage" : "0x470000",
  "timestamp" : "0xaf0ada7a",
  "il_offset" : "0x00000"
 }
,
{
  "is_managed" : "false",
  "native_address" : "0x13d695b74",
  "native_offset" : "0x00000"
 }
,
{
  "is_managed" : "false",
  "native_address" : "0x13d81b7ec",
  "native_offset" : "0x00000"
 }
,
{
  "is_managed" : "false",
  "native_address" : "0x13d81d3e8",
  "native_offset" : "0x00000"
 }
,
{
  "is_managed" : "false",
  "native_address" : "0x13d83d72c",
  "native_offset" : "0x00000"
 }
,
{
  "is_managed" : "false",
  "native_address" : "0x13d83d4e4",
  "native_offset" : "0x00000"
 }
,
{
  "is_managed" : "false",
  "native_address" : "0x13d8bcd30",
  "native_offset" : "0x00000"
 }
,
{
  "is_managed" : "false",
  "native_address" : "0x13d8bccb8",
  "native_offset" : "0x00000"
 }
,
{
  "is_managed" : "false",
  "native_address" : "0x1a380226c",
  "native_offset" : "0x00000"
 }
,
{
  "is_managed" : "false",
  "native_address" : "0x1a37fd08c",
  "native_offset" : "0x00000"
 }

]
},
{
"is_managed" : false,
"offset_free_hash" : "0x0",
"offset_rich_hash" : "0x0",
"crashed" : false,
"native_thread_id" : "0x17fbd3000",
"thread_info_addr" : "0x14a190e00",
"thread_name" : "Debugger agent",
"ctx" : {
  "IP" : "0x1a37ccea4",
  "SP" : "0x17fbd2aa0",
  "BP" : "0x17fbd2ae0"
},
"unmanaged_frames" : [
{
  "is_managed" : "false",
  "native_address" : "0x13d705ec0",
  "native_offset" : "0x00000"
 }
,
{
  "is_managed" : "false",
  "native_address" : "0x13d83c8cc",
  "native_offset" : "0x00000"
 }
,
{
  "is_managed" : "false",
  "native_address" : "0x13d83cc28",
  "native_offset" : "0x00000"
 }
,
{
  "is_managed" : "false",
  "native_address" : "0x13d83c9f0",
  "native_offset" : "0x00000"
 }
,
{
  "is_managed" : "false",
  "native_address" : "0x13d746dc8",
  "native_offset" : "0x00000"
 }
,
{
  "is_managed" : "false",
  "native_address" : "0x1a38194c4",
  "native_offset" : "0x00000"
 }
,
{
  "is_managed" : "false",
  "native_address" : "0x13d77c5d4",
  "native_offset" : "0x00000"
 }
,
{
  "is_managed" : "false",
  "native_address" : "0x13d773954",
  "native_offset" : "0x00000"
 }
,
{
  "is_managed" : "false",
  "native_address" : "0x13d83d638",
  "native_offset" : "0x00000"
 }
,
{
  "is_managed" : "false",
  "native_address" : "0x13d83d4e4",
  "native_offset" : "0x00000"
 }
,
{
  "is_managed" : "false",
  "native_address" : "0x13d8bcd30",
  "native_offset" : "0x00000"
 }
,
{
  "is_managed" : "false",
  "native_address" : "0x13d8bccb8",
  "native_offset" : "0x00000"
 }
,
{
  "is_managed" : "false",
  "native_address" : "0x1a380226c",
  "native_offset" : "0x00000"
 }
,
{
  "is_managed" : "false",
  "native_address" : "0x1a37fd08c",
  "native_offset" : "0x00000"
 }

]
},
{
"is_managed" : false,
"offset_free_hash" : "0x0",
"offset_rich_hash" : "0x0",
"crashed" : false,
"native_thread_id" : "0x2c6cd3000",
"thread_info_addr" : "0x3286d3a00",
"thread_name" : "Thread Pool Worker",
"ctx" : {
  "IP" : "0x1a37c4924",
  "SP" : "0x2c6cd2db0",
  "BP" : "0x2c6cd2e50"
},
"unmanaged_frames" : [
{
  "is_managed" : "false",
  "native_address" : "0x13d705ec0",
  "native_offset" : "0x00000"
 }
,
{
  "is_managed" : "false",
  "native_address" : "0x13d83c8cc",
  "native_offset" : "0x00000"
 }
,
{
  "is_managed" : "false",
  "native_address" : "0x13d83cc28",
  "native_offset" : "0x00000"
 }
,
{
  "is_managed" : "false",
  "native_address" : "0x13d83c9f0",
  "native_offset" : "0x00000"
 }
,
{
  "is_managed" : "false",
  "native_address" : "0x13d746dc8",
  "native_offset" : "0x00000"
 }
,
{
  "is_managed" : "false",
  "native_address" : "0x1a38194c4",
  "native_offset" : "0x00000"
 }
,
{
  "is_managed" : "false",
  "native_address" : "0x13d794e4c",
  "native_offset" : "0x00000"
 }
,
{
  "is_managed" : "false",
  "native_address" : "0x13d83d638",
  "native_offset" : "0x00000"
 }
,
{
  "is_managed" : "false",
  "native_address" : "0x13d83d4e4",
  "native_offset" : "0x00000"
 }
,
{
  "is_managed" : "false",
  "native_address" : "0x13d8bcd30",
  "native_offset" : "0x00000"
 }
,
{
  "is_managed" : "false",
  "native_address" : "0x13d8bccb8",
  "native_offset" : "0x00000"
 }
,
{
  "is_managed" : "false",
  "native_address" : "0x1a380226c",
  "native_offset" : "0x00000"
 }
,
{
  "is_managed" : "false",
  "native_address" : "0x1a37fd08c",
  "native_offset" : "0x00000"
 }

]
},
{
"is_managed" : true,
"offset_free_hash" : "0x1338ab8306",
"offset_rich_hash" : "0x1338ab84fd",
"crashed" : false,
"native_thread_id" : "0x2ea447000",
"thread_info_addr" : "0x3288f8e00",
"thread_name" : "tid_51007",
"ctx" : {
  "IP" : "0x1a37c8290",
  "SP" : "0x2ea4464a0",
  "BP" : "0x2ea446530"
},
"managed_frames" : [
{
  "is_managed" : "false",
  "native_address" : "unregistered"
 }
,
{
  "is_managed" : "true",
  "guid" : "E38A6D3E-E47C-43EB-9B2E-49C63FC0AA48",
  "token" : "0x00000",
  "native_offset" : "0x0",
  "filename" : "mscorlib.dll",
  "sizeofimage" : "0x470000",
  "timestamp" : "0xaf0ada7a",
  "il_offset" : "0xffffffff"
 }
,
{
  "is_managed" : "true",
  "guid" : "E38A6D3E-E47C-43EB-9B2E-49C63FC0AA48",
  "token" : "0x6001f5d",
  "native_offset" : "0x0",
  "filename" : "mscorlib.dll",
  "sizeofimage" : "0x470000",
  "timestamp" : "0xaf0ada7a",
  "il_offset" : "0x0002f"
 }
,
{
  "is_managed" : "true",
  "guid" : "E38A6D3E-E47C-43EB-9B2E-49C63FC0AA48",
  "token" : "0x6001f50",
  "native_offset" : "0x0",
  "filename" : "mscorlib.dll",
  "sizeofimage" : "0x470000",
  "timestamp" : "0xaf0ada7a",
  "il_offset" : "0x0000e"
 }
,
{
  "is_managed" : "true",
  "guid" : "E38A6D3E-E47C-43EB-9B2E-49C63FC0AA48",
  "token" : "0x6001f52",
  "native_offset" : "0x0",
  "filename" : "mscorlib.dll",
  "sizeofimage" : "0x470000",
  "timestamp" : "0xaf0ada7a",
  "il_offset" : "0x00000"
 }
,
{
  "is_managed" : "true",
  "guid" : "C367E0BC-B6D4-43AA-B744-A88F98B1F317",
  "token" : "0x6003f83",
  "native_offset" : "0x0",
  "filename" : "unityplastic.dll",
  "sizeofimage" : "0x4c8000",
  "timestamp" : "0x62434843",
  "il_offset" : "0x00014"
 }
,
{
  "is_managed" : "true",
  "guid" : "C367E0BC-B6D4-43AA-B744-A88F98B1F317",
  "token" : "0x6003f82",
  "native_offset" : "0x0",
  "filename" : "unityplastic.dll",
  "sizeofimage" : "0x4c8000",
  "timestamp" : "0x62434843",
  "il_offset" : "0x0008a"
 }
,
{
  "is_managed" : "true",
  "guid" : "C367E0BC-B6D4-43AA-B744-A88F98B1F317",
  "token" : "0x6003f86",
  "native_offset" : "0x0",
  "filename" : "unityplastic.dll",
  "sizeofimage" : "0x4c8000",
  "timestamp" : "0x62434843",
  "il_offset" : "0x00000"
 }
,
{
  "is_managed" : "true",
  "guid" : "E38A6D3E-E47C-43EB-9B2E-49C63FC0AA48",
  "token" : "0x6001f7d",
  "native_offset" : "0x0",
  "filename" : "mscorlib.dll",
  "sizeofimage" : "0x470000",
  "timestamp" : "0xaf0ada7a",
  "il_offset" : "0x00014"
 }
,
{
  "is_managed" : "true",
  "guid" : "E38A6D3E-E47C-43EB-9B2E-49C63FC0AA48",
  "token" : "0x6001f25",
  "native_offset" : "0x0",
  "filename" : "mscorlib.dll",
  "sizeofimage" : "0x470000",
  "timestamp" : "0xaf0ada7a",
  "il_offset" : "0x00071"
 }
,
{
  "is_managed" : "true",
  "guid" : "E38A6D3E-E47C-43EB-9B2E-49C63FC0AA48",
  "token" : "0x6001f23",
  "native_offset" : "0x0",
  "filename" : "mscorlib.dll",
  "sizeofimage" : "0x470000",
  "timestamp" : "0xaf0ada7a",
  "il_offset" : "0x00000"
 }
,
{
  "is_managed" : "true",
  "guid" : "E38A6D3E-E47C-43EB-9B2E-49C63FC0AA48",
  "token" : "0x6001f22",
  "native_offset" : "0x0",
  "filename" : "mscorlib.dll",
  "sizeofimage" : "0x470000",
  "timestamp" : "0xaf0ada7a",
  "il_offset" : "0x0002b"
 }
,
{
  "is_managed" : "true",
  "guid" : "E38A6D3E-E47C-43EB-9B2E-49C63FC0AA48",
  "token" : "0x6001f7f",
  "native_offset" : "0x0",
  "filename" : "mscorlib.dll",
  "sizeofimage" : "0x470000",
  "timestamp" : "0xaf0ada7a",
  "il_offset" : "0x00008"
 }
,
{
  "is_managed" : "true",
  "guid" : "E38A6D3E-E47C-43EB-9B2E-49C63FC0AA48",
  "token" : "0x00000",
  "native_offset" : "0x0",
  "filename" : "mscorlib.dll",
  "sizeofimage" : "0x470000",
  "timestamp" : "0xaf0ada7a",
  "il_offset" : "0x00065"
 }

],
"unmanaged_frames" : [
{
"is_managed" : "false",
"native_address" : "0x13d705ec0",
"native_offset" : "0x00000"
}
,
{
"is_managed" : "false",
"native_address" : "0x13d83c8cc",
"native_offset" : "0x00000"
}
,
{
"is_managed" : "false",
"native_address" : "0x13d83cc28",
"native_offset" : "0x00000"
}
,
{
"is_managed" : "false",
"native_address" : "0x13d83c9f0",
"native_offset" : "0x00000"
}
,
{
"is_managed" : "false",
"native_address" : "0x13d746dc8",
"native_offset" : "0x00000"
}
,
{
"is_managed" : "false",
"native_address" : "0x1a38194c4",
"native_offset" : "0x00000"
}
,
{
"is_managed" : "false",
"native_address" : "0x1a3802868",
"native_offset" : "0x00000"
}
,
{
"is_managed" : "false",
"native_address" : "0x13d88beac",
"native_offset" : "0x00000"
}
,
{
"is_managed" : "false",
"native_address" : "0x13d8485f4",
"native_offset" : "0x00000"
}
,
{
"is_managed" : "false",
"native_address" : "0x13d848428",
"native_offset" : "0x00000"
}
,
{
"is_managed" : "false",
"native_address" : "0x13d8776f8",
"native_offset" : "0x00000"
}
,
{
"is_managed" : "false",
"native_address" : "0x13d7e0dfc",
"native_offset" : "0x00000"
}
,
{
"is_managed" : "true",
"guid" : "E38A6D3E-E47C-43EB-9B2E-49C63FC0AA48",
"token" : "0x00000",
"native_offset" : "0x0",
"filename" : "mscorlib.dll",
"sizeofimage" : "0x470000",
"timestamp" : "0xaf0ada7a",
"il_offset" : "0x00000"
}
,
{
"is_managed" : "true",
"guid" : "E38A6D3E-E47C-43EB-9B2E-49C63FC0AA48",
"token" : "0x6001f5d",
"native_offset" : "0x0",
"filename" : "mscorlib.dll",
"sizeofimage" : "0x470000",
"timestamp" : "0xaf0ada7a",
"il_offset" : "0x00000"
}
,
{
"is_managed" : "true",
"guid" : "E38A6D3E-E47C-43EB-9B2E-49C63FC0AA48",
"token" : "0x6001f50",
"native_offset" : "0x0",
"filename" : "mscorlib.dll",
"sizeofimage" : "0x470000",
"timestamp" : "0xaf0ada7a",
"il_offset" : "0x00000"
}
,
{
"is_managed" : "true",
"guid" : "E38A6D3E-E47C-43EB-9B2E-49C63FC0AA48",
"token" : "0x6001f52",
"native_offset" : "0x0",
"filename" : "mscorlib.dll",
"sizeofimage" : "0x470000",
"timestamp" : "0xaf0ada7a",
"il_offset" : "0x00000"
}
,
{
"is_managed" : "true",
"guid" : "C367E0BC-B6D4-43AA-B744-A88F98B1F317",
"token" : "0x6003f83",
"native_offset" : "0x0",
"filename" : "unityplastic.dll",
"sizeofimage" : "0x4c8000",
"timestamp" : "0x62434843",
"il_offset" : "0x00000"
}
,
{
"is_managed" : "true",
"guid" : "C367E0BC-B6D4-43AA-B744-A88F98B1F317",
"token" : "0x6003f82",
"native_offset" : "0x0",
"filename" : "unityplastic.dll",
"sizeofimage" : "0x4c8000",
"timestamp" : "0x62434843",
"il_offset" : "0x00000"
}
,
{
"is_managed" : "true",
"guid" : "C367E0BC-B6D4-43AA-B744-A88F98B1F317",
"token" : "0x6003f86",
"native_offset" : "0x0",
"filename" : "unityplastic.dll",
"sizeofimage" : "0x4c8000",
"timestamp" : "0x62434843",
"il_offset" : "0x00000"
}
,
{
"is_managed" : "true",
"guid" : "E38A6D3E-E47C-43EB-9B2E-49C63FC0AA48",
"token" : "0x6001f7d",
"native_offset" : "0x0",
"filename" : "mscorlib.dll",
"sizeofimage" : "0x470000",
"timestamp" : "0xaf0ada7a",
"il_offset" : "0x00000"
}
,
{
"is_managed" : "true",
"guid" : "E38A6D3E-E47C-43EB-9B2E-49C63FC0AA48",
"token" : "0x6001f25",
"native_offset" : "0x0",
"filename" : "mscorlib.dll",
"sizeofimage" : "0x470000",
"timestamp" : "0xaf0ada7a",
"il_offset" : "0x00000"
}
,
{
"is_managed" : "true",
"guid" : "E38A6D3E-E47C-43EB-9B2E-49C63FC0AA48",
"token" : "0x6001f23",
"native_offset" : "0x0",
"filename" : "mscorlib.dll",
"sizeofimage" : "0x470000",
"timestamp" : "0xaf0ada7a",
"il_offset" : "0x00000"
}
,
{
"is_managed" : "true",
"guid" : "E38A6D3E-E47C-43EB-9B2E-49C63FC0AA48",
"token" : "0x6001f22",
"native_offset" : "0x0",
"filename" : "mscorlib.dll",
"sizeofimage" : "0x470000",
"timestamp" : "0xaf0ada7a",
"il_offset" : "0x00000"
}
,
{
"is_managed" : "true",
"guid" : "E38A6D3E-E47C-43EB-9B2E-49C63FC0AA48",
"token" : "0x6001f7f",
"native_offset" : "0x0",
"filename" : "mscorlib.dll",
"sizeofimage" : "0x470000",
"timestamp" : "0xaf0ada7a",
"il_offset" : "0x00000"
}
,
{
"is_managed" : "true",
"guid" : "E38A6D3E-E47C-43EB-9B2E-49C63FC0AA48",
"token" : "0x00000",
"native_offset" : "0x0",
"filename" : "mscorlib.dll",
"sizeofimage" : "0x470000",
"timestamp" : "0xaf0ada7a",
"il_offset" : "0x00000"
}
,
{
"is_managed" : "false",
"native_address" : "0x13d695b74",
"native_offset" : "0x00000"
}
,
{
"is_managed" : "false",
"native_address" : "0x13d81b7ec",
"native_offset" : "0x00000"
}
,
{
"is_managed" : "false",
"native_address" : "0x13d81d3e8",
"native_offset" : "0x00000"
}
,
{
"is_managed" : "false",
"native_address" : "0x13d83d72c",
"native_offset" : "0x00000"
}
,
{
"is_managed" : "false",
"native_address" : "0x13d83d4e4",
"native_offset" : "0x00000"
}
,
{
"is_managed" : "false",
"native_address" : "0x13d8bcd30",
"native_offset" : "0x00000"
}
,
{
"is_managed" : "false",
"native_address" : "0x13d8bccb8",
"native_offset" : "0x00000"
}
,
{
"is_managed" : "false",
"native_address" : "0x1a380226c",
"native_offset" : "0x00000"
}
,
{
"is_managed" : "false",
"native_address" : "0x1a37fd08c",
"native_offset" : "0x00000"
}

]
},
{
"is_managed" : true,
"offset_free_hash" : "0x11757b44be",
"offset_rich_hash" : "0x11757b466a",
"crashed" : false,
"native_thread_id" : "0x2eb6db000",
"thread_info_addr" : "0x3281dd800",
"thread_name" : "tid_50f03",
"ctx" : {
"IP" : "0x1a37c8290",
"SP" : "0x2eb6da4a0",
"BP" : "0x2eb6da530"
},
"managed_frames" : [
{
"is_managed" : "false",
"native_address" : "unregistered"
}
,
{
"is_managed" : "true",
"guid" : "E38A6D3E-E47C-43EB-9B2E-49C63FC0AA48",
"token" : "0x00000",
"native_offset" : "0x0",
"filename" : "mscorlib.dll",
"sizeofimage" : "0x470000",
"timestamp" : "0xaf0ada7a",
"il_offset" : "0xffffffff"
}
,
{
"is_managed" : "true",
"guid" : "E38A6D3E-E47C-43EB-9B2E-49C63FC0AA48",
"token" : "0x6001f5d",
"native_offset" : "0x0",
"filename" : "mscorlib.dll",
"sizeofimage" : "0x470000",
"timestamp" : "0xaf0ada7a",
"il_offset" : "0x0002f"
}
,
{
"is_managed" : "true",
"guid" : "E38A6D3E-E47C-43EB-9B2E-49C63FC0AA48",
"token" : "0x6001f50",
"native_offset" : "0x0",
"filename" : "mscorlib.dll",
"sizeofimage" : "0x470000",
"timestamp" : "0xaf0ada7a",
"il_offset" : "0x0000e"
}
,
{
"is_managed" : "true",
"guid" : "E38A6D3E-E47C-43EB-9B2E-49C63FC0AA48",
"token" : "0x6001f52",
"native_offset" : "0x0",
"filename" : "mscorlib.dll",
"sizeofimage" : "0x470000",
"timestamp" : "0xaf0ada7a",
"il_offset" : "0x00000"
}
,
{
"is_managed" : "true",
"guid" : "C367E0BC-B6D4-43AA-B744-A88F98B1F317",
"token" : "0x600147a",
"native_offset" : "0x0",
"filename" : "unityplastic.dll",
"sizeofimage" : "0x4c8000",
"timestamp" : "0x62434843",
"il_offset" : "0x00014"
}
,
{
"is_managed" : "true",
"guid" : "C367E0BC-B6D4-43AA-B744-A88F98B1F317",
"token" : "0x6001478",
"native_offset" : "0x0",
"filename" : "unityplastic.dll",
"sizeofimage" : "0x4c8000",
"timestamp" : "0x62434843",
"il_offset" : "0x0003f"
}
,
{
"is_managed" : "true",
"guid" : "E38A6D3E-E47C-43EB-9B2E-49C63FC0AA48",
"token" : "0x6001f7d",
"native_offset" : "0x0",
"filename" : "mscorlib.dll",
"sizeofimage" : "0x470000",
"timestamp" : "0xaf0ada7a",
"il_offset" : "0x00014"
}
,
{
"is_managed" : "true",
"guid" : "E38A6D3E-E47C-43EB-9B2E-49C63FC0AA48",
"token" : "0x6001f25",
"native_offset" : "0x0",
"filename" : "mscorlib.dll",
"sizeofimage" : "0x470000",
"timestamp" : "0xaf0ada7a",
"il_offset" : "0x00071"
}
,
{
"is_managed" : "true",
"guid" : "E38A6D3E-E47C-43EB-9B2E-49C63FC0AA48",
"token" : "0x6001f23",
"native_offset" : "0x0",
"filename" : "mscorlib.dll",
"sizeofimage" : "0x470000",
"timestamp" : "0xaf0ada7a",
"il_offset" : "0x00000"
}
,
{
"is_managed" : "true",
"guid" : "E38A6D3E-E47C-43EB-9B2E-49C63FC0AA48",
"token" : "0x6001f22",
"native_offset" : "0x0",
"filename" : "mscorlib.dll",
"sizeofimage" : "0x470000",
"timestamp" : "0xaf0ada7a",
"il_offset" : "0x0002b"
}
,
{
"is_managed" : "true",
"guid" : "E38A6D3E-E47C-43EB-9B2E-49C63FC0AA48",
"token" : "0x6001f7f",
"native_offset" : "0x0",
"filename" : "mscorlib.dll",
"sizeofimage" : "0x470000",
"timestamp" : "0xaf0ada7a",
"il_offset" : "0x00008"
}
,
{
"is_managed" : "true",
"guid" : "E38A6D3E-E47C-43EB-9B2E-49C63FC0AA48",
"token" : "0x00000",
"native_offset" : "0x0",
"filename" : "mscorlib.dll",
"sizeofimage" : "0x470000",
"timestamp" : "0xaf0ada7a",
"il_offset" : "0x00065"
}

],
"unmanaged_frames" : [
{
"is_managed" : "false",
"native_address" : "0x13d705ec0",
"native_offset" : "0x00000"
}
,
{
"is_managed" : "false",
"native_address" : "0x13d83c8cc",
"native_offset" : "0x00000"
}
,
{
"is_managed" : "false",
"native_address" : "0x13d83cc28",
"native_offset" : "0x00000"
}
,
{
"is_managed" : "false",
"native_address" : "0x13d83c9f0",
"native_offset" : "0x00000"
}
,
{
"is_managed" : "false",
"native_address" : "0x13d746dc8",
"native_offset" : "0x00000"
}
,
{
"is_managed" : "false",
"native_address" : "0x1a38194c4",
"native_offset" : "0x00000"
}
,
{
"is_managed" : "false",
"native_address" : "0x1a3802868",
"native_offset" : "0x00000"
}
,
{
"is_managed" : "false",
"native_address" : "0x13d88beac",
"native_offset" : "0x00000"
}
,
{
"is_managed" : "false",
"native_address" : "0x13d8485f4",
"native_offset" : "0x00000"
}
,
{
"is_managed" : "false",
"native_address" : "0x13d848428",
"native_offset" : "0x00000"
}
,
{
"is_managed" : "false",
"native_address" : "0x13d8776f8",
"native_offset" : "0x00000"
}
,
{
"is_managed" : "false",
"native_address" : "0x13d7e0dfc",
"native_offset" : "0x00000"
}
,
{
"is_managed" : "true",
"guid" : "E38A6D3E-E47C-43EB-9B2E-49C63FC0AA48",
"token" : "0x00000",
"native_offset" : "0x0",
"filename" : "mscorlib.dll",
"sizeofimage" : "0x470000",
"timestamp" : "0xaf0ada7a",
"il_offset" : "0x00000"
}
,
{
"is_managed" : "true",
"guid" : "E38A6D3E-E47C-43EB-9B2E-49C63FC0AA48",
"token" : "0x6001f5d",
"native_offset" : "0x0",
"filename" : "mscorlib.dll",
"sizeofimage" : "0x470000",
"timestamp" : "0xaf0ada7a",
"il_offset" : "0x00000"
}
,
{
"is_managed" : "true",
"guid" : "E38A6D3E-E47C-43EB-9B2E-49C63FC0AA48",
"token" : "0x6001f50",
"native_offset" : "0x0",
"filename" : "mscorlib.dll",
"sizeofimage" : "0x470000",
"timestamp" : "0xaf0ada7a",
"il_offset" : "0x00000"
}
,
{
"is_managed" : "true",
"guid" : "E38A6D3E-E47C-43EB-9B2E-49C63FC0AA48",
"token" : "0x6001f52",
"native_offset" : "0x0",
"filename" : "mscorlib.dll",
"sizeofimage" : "0x470000",
"timestamp" : "0xaf0ada7a",
"il_offset" : "0x00000"
}
,
{
"is_managed" : "true",
"guid" : "C367E0BC-B6D4-43AA-B744-A88F98B1F317",
"token" : "0x600147a",
"native_offset" : "0x0",
"filename" : "unityplastic.dll",
"sizeofimage" : "0x4c8000",
"timestamp" : "0x62434843",
"il_offset" : "0x00000"
}
,
{
"is_managed" : "true",
"guid" : "C367E0BC-B6D4-43AA-B744-A88F98B1F317",
"token" : "0x6001478",
"native_offset" : "0x0",
"filename" : "unityplastic.dll",
"sizeofimage" : "0x4c8000",
"timestamp" : "0x62434843",
"il_offset" : "0x00000"
}
,
{
"is_managed" : "true",
"guid" : "E38A6D3E-E47C-43EB-9B2E-49C63FC0AA48",
"token" : "0x6001f7d",
"native_offset" : "0x0",
"filename" : "mscorlib.dll",
"sizeofimage" : "0x470000",
"timestamp" : "0xaf0ada7a",
"il_offset" : "0x00000"
}
,
{
"is_managed" : "true",
"guid" : "E38A6D3E-E47C-43EB-9B2E-49C63FC0AA48",
"token" : "0x6001f25",
"native_offset" : "0x0",
"filename" : "mscorlib.dll",
"sizeofimage" : "0x470000",
"timestamp" : "0xaf0ada7a",
"il_offset" : "0x00000"
}
,
{
"is_managed" : "true",
"guid" : "E38A6D3E-E47C-43EB-9B2E-49C63FC0AA48",
"token" : "0x6001f23",
"native_offset" : "0x0",
"filename" : "mscorlib.dll",
"sizeofimage" : "0x470000",
"timestamp" : "0xaf0ada7a",
"il_offset" : "0x00000"
}
,
{
"is_managed" : "true",
"guid" : "E38A6D3E-E47C-43EB-9B2E-49C63FC0AA48",
"token" : "0x6001f22",
"native_offset" : "0x0",
"filename" : "mscorlib.dll",
"sizeofimage" : "0x470000",
"timestamp" : "0xaf0ada7a",
"il_offset" : "0x00000"
}
,
{
"is_managed" : "true",
"guid" : "E38A6D3E-E47C-43EB-9B2E-49C63FC0AA48",
"token" : "0x6001f7f",
"native_offset" : "0x0",
"filename" : "mscorlib.dll",
"sizeofimage" : "0x470000",
"timestamp" : "0xaf0ada7a",
"il_offset" : "0x00000"
}
,
{
"is_managed" : "true",
"guid" : "E38A6D3E-E47C-43EB-9B2E-49C63FC0AA48",
"token" : "0x00000",
"native_offset" : "0x0",
"filename" : "mscorlib.dll",
"sizeofimage" : "0x470000",
"timestamp" : "0xaf0ada7a",
"il_offset" : "0x00000"
}
,
{
"is_managed" : "false",
"native_address" : "0x13d695b74",
"native_offset" : "0x00000"
}
,
{
"is_managed" : "false",
"native_address" : "0x13d81b7ec",
"native_offset" : "0x00000"
}
,
{
"is_managed" : "false",
"native_address" : "0x13d81d3e8",
"native_offset" : "0x00000"
}
,
{
"is_managed" : "false",
"native_address" : "0x13d83d72c",
"native_offset" : "0x00000"
}
,
{
"is_managed" : "false",
"native_address" : "0x13d83d4e4",
"native_offset" : "0x00000"
}
,
{
"is_managed" : "false",
"native_address" : "0x13d8bcd30",
"native_offset" : "0x00000"
}
,
{
"is_managed" : "false",
"native_address" : "0x13d8bccb8",
"native_offset" : "0x00000"
}
,
{
"is_managed" : "false",
"native_address" : "0x1a380226c",
"native_offset" : "0x00000"
}
,
{
"is_managed" : "false",
"native_address" : "0x1a37fd08c",
"native_offset" : "0x00000"
}

]
},
{
"is_managed" : false,
"offset_free_hash" : "0x0",
"offset_rich_hash" : "0x0",
"crashed" : true,
"native_thread_id" : "0x108948580",
"thread_info_addr" : "0x14c1c5800",
"thread_name" : "tid_103",
"ctx" : {
"IP" : "0x1053166c0",
"SP" : "0x16d32d260",
"BP" : "0x16d32d280"
},
"unmanaged_frames" : [
{
"is_managed" : "false",
"native_address" : "0x13d705ec0",
"native_offset" : "0x00000"
}
,
{
"is_managed" : "false",
"native_address" : "0x13d83c8cc",
"native_offset" : "0x00000"
}
,
{
"is_managed" : "false",
"native_address" : "0x13d83cc28",
"native_offset" : "0x00000"
}
,
{
"is_managed" : "false",
"native_address" : "0x13d83d218",
"native_offset" : "0x00000"
}
,
{
"is_managed" : "false",
"native_address" : "0x13d747c14",
"native_offset" : "0x00000"
}
,
{
"is_managed" : "false",
"native_address" : "0x13d709f50",
"native_offset" : "0x00000"
}
,
{
"is_managed" : "false",
"native_address" : "0x13d6928b4",
"native_offset" : "0x00000"
}
,
{
"is_managed" : "false",
"native_address" : "0x1a38194c4",
"native_offset" : "0x00000"
}
,
{
"is_managed" : "false",
"native_address" : "0x105316578",
"native_offset" : "0x00000"
}
,
{
"is_managed" : "false",
"native_address" : "0x1a65e2700",
"native_offset" : "0x00000"
}
,
{
"is_managed" : "false",
"native_address" : "0x1a67222d4",
"native_offset" : "0x00000"
}
,
{
"is_managed" : "false",
"native_address" : "0x1a6709600",
"native_offset" : "0x00000"
}
,
{
"is_managed" : "false",
"native_address" : "0x1ac4c4e58",
"native_offset" : "0x00000"
}
,
{
"is_managed" : "false",
"native_address" : "0x1ac4c42dc",
"native_offset" : "0x00000"
}
,
{
"is_managed" : "false",
"native_address" : "0x1ac4da750",
"native_offset" : "0x00000"
}
,
{
"is_managed" : "false",
"native_address" : "0x1ac53b310",
"native_offset" : "0x00000"
}
,
{
"is_managed" : "false",
"native_address" : "0x1ac54a644",
"native_offset" : "0x00000"
}
,
{
"is_managed" : "false",
"native_address" : "0x1ac4c0500",
"native_offset" : "0x00000"
}
,
{
"is_managed" : "false",
"native_address" : "0x1ac4c4e58",
"native_offset" : "0x00000"
}
,
{
"is_managed" : "false",
"native_address" : "0x1ac4c42dc",
"native_offset" : "0x00000"
}
,
{
"is_managed" : "false",
"native_address" : "0x1ac4da750",
"native_offset" : "0x00000"
}
,
{
"is_managed" : "false",
"native_address" : "0x1ac6908fc",
"native_offset" : "0x00000"
}
,
{
"is_managed" : "false",
"native_address" : "0x1ac549f80",
"native_offset" : "0x00000"
}
,
{
"is_managed" : "false",
"native_address" : "0x1ac68df94",
"native_offset" : "0x00000"
}
,
{
"is_managed" : "false",
"native_address" : "0x1dad70290",
"native_offset" : "0x00000"
}
,
{
"is_managed" : "false",
"native_address" : "0x1dad70278",
"native_offset" : "0x00000"
}
,
{
"is_managed" : "false",
"native_address" : "0x1dad6fe40",
"native_offset" : "0x00000"
}
,
{
"is_managed" : "false",
"native_address" : "0x1dad6fbf8",
"native_offset" : "0x00000"
}
,
{
"is_managed" : "false",
"native_address" : "0x1dad71680",
"native_offset" : "0x00000"
}
,
{
"is_managed" : "false",
"native_address" : "0x1a38c2ddc",
"native_offset" : "0x00000"
}
,
{
"is_managed" : "false",
"native_address" : "0x1a3967578",
"native_offset" : "0x00000"
}
,
{
"is_managed" : "false",
"native_address" : "0x1a39674e4",
"native_offset" : "0x00000"
}
,
{
"is_managed" : "false",
"native_address" : "0x1a3891a74",
"native_offset" : "0x00000"
}
,
{
"is_managed" : "false",
"native_address" : "0x1a474ee48",
"native_offset" : "0x00000"
}
,
{
"is_managed" : "false",
"native_address" : "0x1a38c2ddc",
"native_offset" : "0x00000"
}
,
{
"is_managed" : "false",
"native_address" : "0x1a3967578",
"native_offset" : "0x00000"
}
,
{
"is_managed" : "false",
"native_address" : "0x1a39674e4",
"native_offset" : "0x00000"
}
,
{
"is_managed" : "false",
"native_address" : "0x1a3891a74",
"native_offset" : "0x00000"
}
,
{
"is_managed" : "false",
"native_address" : "0x1a474ee48",
"native_offset" : "0x00000"
}
,
{
"is_managed" : "false",
"native_address" : "0x1a663db30",
"native_offset" : "0x00000"
}
,
{
"is_managed" : "false",
"native_address" : "0x1a663af80",
"native_offset" : "0x00000"
}
,
{
"is_managed" : "false",
"native_address" : "0x1a6639f10",
"native_offset" : "0x00000"
}
,
{
"is_managed" : "false",
"native_address" : "0x1a6e08c24",
"native_offset" : "0x00000"
}
,
{
"is_managed" : "false",
"native_address" : "0x1a6639e48",
"native_offset" : "0x00000"
}
,
{
"is_managed" : "false",
"native_address" : "0x1a6639ca4",
"native_offset" : "0x00000"
}
,
{
"is_managed" : "false",
"native_address" : "0x1a6e085e0",
"native_offset" : "0x00000"
}
,
{
"is_managed" : "false",
"native_address" : "0x1a6639844",
"native_offset" : "0x00000"
}
,
{
"is_managed" : "false",
"native_address" : "0x1a6639788",
"native_offset" : "0x00000"
}
,
{
"is_managed" : "false",
"native_address" : "0x1a6638c24",
"native_offset" : "0x00000"
}
,
{
"is_managed" : "false",
"native_address" : "0x1a6638388",
"native_offset" : "0x00000"
}
,
{
"is_managed" : "false",
"native_address" : "0x1ac4c4e58",
"native_offset" : "0x00000"
}
,
{
"is_managed" : "false",
"native_address" : "0x1ac4c42dc",
"native_offset" : "0x00000"
}
,
{
"is_managed" : "false",
"native_address" : "0x1ac4c416c",
"native_offset" : "0x00000"
}
,
{
"is_managed" : "false",
"native_address" : "0x1ac52325c",
"native_offset" : "0x00000"
}
,
{
"is_managed" : "false",
"native_address" : "0x1ac523774",
"native_offset" : "0x00000"
}
,
{
"is_managed" : "false",
"native_address" : "0x1ac523580",
"native_offset" : "0x00000"
}
,
{
"is_managed" : "false",
"native_address" : "0x1ac5232b4",
"native_offset" : "0x00000"
}
,
{
"is_managed" : "false",
"native_address" : "0x1ac523024",
"native_offset" : "0x00000"
}
,
{
"is_managed" : "false",
"native_address" : "0x1ac522c4c",
"native_offset" : "0x00000"
}
,
{
"is_managed" : "false",
"native_address" : "0x1ac5229d8",
"native_offset" : "0x00000"
}
,
{
"is_managed" : "false",
"native_address" : "0x1ac52275c",
"native_offset" : "0x00000"
}
,
{
"is_managed" : "false",
"native_address" : "0x1ac5225e0",
"native_offset" : "0x00000"
}
,
{
"is_managed" : "false",
"native_address" : "0x1ac522360",
"native_offset" : "0x00000"
}
,
{
"is_managed" : "false",
"native_address" : "0x1ac522170",
"native_offset" : "0x00000"
}
,
{
"is_managed" : "false",
"native_address" : "0x1ac521e74",
"native_offset" : "0x00000"
}
,
{
"is_managed" : "false",
"native_address" : "0x1ac521b78",
"native_offset" : "0x00000"
}
,
{
"is_managed" : "false",
"native_address" : "0x1ac50fe20",
"native_offset" : "0x00000"
}
,
{
"is_managed" : "false",
"native_address" : "0x1a6e0cf8c",
"native_offset" : "0x00000"
}
,
{
"is_managed" : "false",
"native_address" : "0x1a6e0cc40",
"native_offset" : "0x00000"
}
,
{
"is_managed" : "false",
"native_address" : "0x1a6636e14",
"native_offset" : "0x00000"
}
,
{
"is_managed" : "false",
"native_address" : "0x1a6636704",
"native_offset" : "0x00000"
}
,
{
"is_managed" : "false",
"native_address" : "0x1a66360cc",
"native_offset" : "0x00000"
}
,
{
"is_managed" : "false",
"native_address" : "0x1a6635ee8",
"native_offset" : "0x00000"
}
,
{
"is_managed" : "false",
"native_address" : "0x1a6635cf8",
"native_offset" : "0x00000"
}
,
{
"is_managed" : "false",
"native_address" : "0x1a659d47c",
"native_offset" : "0x00000"
}
,
{
"is_managed" : "false",
"native_address" : "0x1a659bb00",
"native_offset" : "0x00000"
}
,
{
"is_managed" : "false",
"native_address" : "0x1a6a73e0c",
"native_offset" : "0x00000"
}
,
{
"is_managed" : "false",
"native_address" : "0x1a6d48e54",
"native_offset" : "0x00000"
}
,
{
"is_managed" : "false",
"native_address" : "0x1ac4c4e58",
"native_offset" : "0x00000"
}
,
{
"is_managed" : "false",
"native_address" : "0x1ac4c42dc",
"native_offset" : "0x00000"
}

]
},
{
"is_managed" : false,
"offset_free_hash" : "0x0",
"offset_rich_hash" : "0x0",
"crashed" : false,
"native_thread_id" : "0x2c5fd3000",
"thread_info_addr" : "0x328613800",
"thread_name" : "Thread Pool Worker",
"ctx" : {
"IP" : "0x1a37c4924",
"SP" : "0x2c5fd2db0",
"BP" : "0x2c5fd2e50"
},
"unmanaged_frames" : [
{
"is_managed" : "false",
"native_address" : "0x13d705ec0",
"native_offset" : "0x00000"
}
,
{
"is_managed" : "false",
"native_address" : "0x13d83c8cc",
"native_offset" : "0x00000"
}
,
{
"is_managed" : "false",
"native_address" : "0x13d83cc28",
"native_offset" : "0x00000"
}
,
{
"is_managed" : "false",
"native_address" : "0x13d83c9f0",
"native_offset" : "0x00000"
}
,
{
"is_managed" : "false",
"native_address" : "0x13d746dc8",
"native_offset" : "0x00000"
}
,
{
"is_managed" : "false",
"native_address" : "0x1a38194c4",
"native_offset" : "0x00000"
}
,
{
"is_managed" : "false",
"native_address" : "0x13d794e4c",
"native_offset" : "0x00000"
}
,
{
"is_managed" : "false",
"native_address" : "0x13d83d638",
"native_offset" : "0x00000"
}
,
{
"is_managed" : "false",
"native_address" : "0x13d83d4e4",
"native_offset" : "0x00000"
}
,
{
"is_managed" : "false",
"native_address" : "0x13d8bcd30",
"native_offset" : "0x00000"
}
,
{
"is_managed" : "false",
"native_address" : "0x13d8bccb8",
"native_offset" : "0x00000"
}
,
{
"is_managed" : "false",
"native_address" : "0x1a380226c",
"native_offset" : "0x00000"
}
,
{
"is_managed" : "false",
"native_address" : "0x1a37fd08c",
"native_offset" : "0x00000"
}

]
},
{
"is_managed" : false,
"offset_free_hash" : "0x0",
"offset_rich_hash" : "0x0",
"crashed" : false,
"native_thread_id" : "0x2c6d73000",
"thread_info_addr" : "0x14b4bf200",
"thread_name" : "tid_2d117",
"ctx" : {
"IP" : "0x1a37c490c",
"SP" : "0x2c6d72d80",
"BP" : "0x2c6d72d90"
},
"unmanaged_frames" : [
{
"is_managed" : "false",
"native_address" : "0x13d705ec0",
"native_offset" : "0x00000"
}
,
{
"is_managed" : "false",
"native_address" : "0x13d83c8cc",
"native_offset" : "0x00000"
}
,
{
"is_managed" : "false",
"native_address" : "0x13d83cc28",
"native_offset" : "0x00000"
}
,
{
"is_managed" : "false",
"native_address" : "0x13d83c9f0",
"native_offset" : "0x00000"
}
,
{
"is_managed" : "false",
"native_address" : "0x13d746dc8",
"native_offset" : "0x00000"
}
,
{
"is_managed" : "false",
"native_address" : "0x1a38194c4",
"native_offset" : "0x00000"
}
,
{
"is_managed" : "false",
"native_address" : "0x1a363e74c",
"native_offset" : "0x00000"
}
,
{
"is_managed" : "false",
"native_address" : "0x1a363edf4",
"native_offset" : "0x00000"
}
,
{
"is_managed" : "false",
"native_address" : "0x1054cf490",
"native_offset" : "0x00000"
}
,
{
"is_managed" : "false",
"native_address" : "0x103035ad0",
"native_offset" : "0x00000"
}
,
{
"is_managed" : "false",
"native_address" : "0x1033d9a58",
"native_offset" : "0x00000"
}
,
{
"is_managed" : "false",
"native_address" : "0x1033d99f4",
"native_offset" : "0x00000"
}
,
{
"is_managed" : "false",
"native_address" : "0x10355b8e0",
"native_offset" : "0x00000"
}
,
{
"is_managed" : "false",
"native_address" : "0x1a380226c",
"native_offset" : "0x00000"
}
,
{
"is_managed" : "false",
"native_address" : "0x1a37fd08c",
"native_offset" : "0x00000"
}

]
},
{
"is_managed" : false,
"offset_free_hash" : "0x0",
"offset_rich_hash" : "0x0",
"crashed" : false,
"native_thread_id" : "0x2c72bb000",
"thread_info_addr" : "0x328704200",
"thread_name" : "tid_301eb",
"ctx" : {
"IP" : "0x1a37c4924",
"SP" : "0x2c72badb0",
"BP" : "0x2c72bae50"
},
"unmanaged_frames" : [
{
"is_managed" : "false",
"native_address" : "0x13d705ec0",
"native_offset" : "0x00000"
}
,
{
"is_managed" : "false",
"native_address" : "0x13d83c8cc",
"native_offset" : "0x00000"
}
,
{
"is_managed" : "false",
"native_address" : "0x13d83cc28",
"native_offset" : "0x00000"
}
,
{
"is_managed" : "false",
"native_address" : "0x13d83c9f0",
"native_offset" : "0x00000"
}
,
{
"is_managed" : "false",
"native_address" : "0x13d746dc8",
"native_offset" : "0x00000"
}
,
{
"is_managed" : "false",
"native_address" : "0x1a38194c4",
"native_offset" : "0x00000"
}
,
{
"is_managed" : "false",
"native_address" : "0x13d794e4c",
"native_offset" : "0x00000"
}
,
{
"is_managed" : "false",
"native_address" : "0x13d83d638",
"native_offset" : "0x00000"
}
,
{
"is_managed" : "false",
"native_address" : "0x13d83d4e4",
"native_offset" : "0x00000"
}
,
{
"is_managed" : "false",
"native_address" : "0x13d8bcd30",
"native_offset" : "0x00000"
}
,
{
"is_managed" : "false",
"native_address" : "0x13d8bccb8",
"native_offset" : "0x00000"
}
,
{
"is_managed" : "false",
"native_address" : "0x1a380226c",
"native_offset" : "0x00000"
}
,
{
"is_managed" : "false",
"native_address" : "0x1a37fd08c",
"native_offset" : "0x00000"
}

]
}
]
}